libbbf/__init__.py
libbbf/_bbf.cp312-win_amd64.pyd
libbbf/bbf2cbx.py
libbbf/cbx2bbf.py
libbbf/exceptions.py
libbbf-0.3.0.dist-info/METADATA
libbbf-0.3.0.dist-info/WHEEL
libbbf-0.3.0.dist-info/entry_points.txt
libbbf-0.3.0.dist-info/top_level.txt
libbbf-0.3.0.dist-info/RECORD
