Metadata-Version: 2.2
Name: libbbf
Version: 0.3.0
Summary: Bound Book Format (BBF) tools and bindings
Home-page: https://github.com/ef1500/libbbf
Author: EF1500
Author-email: rosemilovelockofficial@proton.me
Requires-Python: >=3.11
Dynamic: author
Dynamic: author-email
Dynamic: description
Dynamic: description-content-type
Dynamic: home-page
Dynamic: requires-python
Dynamic: summary
